<?xml version="1.0" ?>
<Gesture Name="right_sq_bracket~02" Subject="5" Number="2" NumPts="69" InputType="Trackpad" Speed="MEDIUM">
    <Stroke index="1">
        <Point X="118" Y="137" T="0"/>
        <Point X="120" Y="136" T="0"/>
        <Point X="122" Y="136" T="0"/>
        <Point X="124" Y="136" T="0"/>
        <Point X="126" Y="136" T="0"/>
        <Point X="128" Y="136" T="0"/>
        <Point X="130" Y="136" T="0"/>
        <Point X="132" Y="135" T="0"/>
        <Point X="135" Y="135" T="0"/>
        <Point X="137" Y="134" T="0"/>
        <Point X="139" Y="135" T="0"/>
        <Point X="142" Y="135" T="0"/>
        <Point X="144" Y="135" T="0"/>
        <Point X="147" Y="134" T="0"/>
        <Point X="149" Y="133" T="0"/>
        <Point X="152" Y="134" T="0"/>
        <Point X="154" Y="133" T="0"/>
        <Point X="156" Y="133" T="0"/>
        <Point X="158" Y="134" T="0"/>
        <Point X="159" Y="136" T="0"/>
        <Point X="158" Y="138" T="0"/>
        <Point X="158" Y="141" T="0"/>
        <Point X="158" Y="143" T="0"/>
        <Point X="158" Y="145" T="0"/>
        <Point X="158" Y="147" T="0"/>
        <Point X="158" Y="149" T="0"/>
        <Point X="158" Y="152" T="0"/>
        <Point X="158" Y="154" T="0"/>
        <Point X="158" Y="158" T="0"/>
        <Point X="158" Y="164" T="0"/>
        <Point X="158" Y="168" T="0"/>
        <Point X="158" Y="176" T="0"/>
        <Point X="158" Y="181" T="0"/>
        <Point X="157" Y="187" T="0"/>
        <Point X="157" Y="193" T="0"/>
        <Point X="156" Y="197" T="0"/>
        <Point X="156" Y="200" T="0"/>
        <Point X="156" Y="207" T="0"/>
        <Point X="155" Y="209" T="0"/>
        <Point X="155" Y="216" T="0"/>
        <Point X="155" Y="219" T="0"/>
        <Point X="154" Y="226" T="0"/>
        <Point X="154" Y="229" T="0"/>
        <Point X="153" Y="236" T="0"/>
        <Point X="153" Y="241" T="0"/>
        <Point X="153" Y="244" T="0"/>
        <Point X="153" Y="247" T="0"/>
        <Point X="153" Y="249" T="0"/>
        <Point X="153" Y="251" T="0"/>
        <Point X="153" Y="253" T="0"/>
        <Point X="153" Y="255" T="0"/>
        <Point X="152" Y="257" T="0"/>
        <Point X="150" Y="258" T="0"/>
        <Point X="147" Y="257" T="0"/>
        <Point X="145" Y="257" T="0"/>
        <Point X="143" Y="256" T="0"/>
        <Point X="138" Y="255" T="0"/>
        <Point X="133" Y="256" T="0"/>
        <Point X="129" Y="255" T="0"/>
        <Point X="124" Y="255" T="0"/>
        <Point X="120" Y="255" T="0"/>
        <Point X="115" Y="254" T="0"/>
        <Point X="113" Y="254" T="0"/>
        <Point X="109" Y="254" T="0"/>
        <Point X="106" Y="253" T="0"/>
        <Point X="104" Y="254" T="0"/>
        <Point X="102" Y="254" T="0"/>
        <Point X="100" Y="254" T="0"/>
        <Point X="98" Y="255" T="0"/>
    </Stroke>
</Gesture>
