<?xml version="1.0" ?>
<Gesture Name="six_point_star10" Subject="4" Number="10" NumPts="266">
    <Stroke index="1">
        <Point X="307" Y="323" T="0"/>
        <Point X="307" Y="321" T="0"/>
        <Point X="306" Y="314" T="0"/>
        <Point X="305" Y="311" T="0"/>
        <Point X="305" Y="307" T="0"/>
        <Point X="305" Y="304" T="0"/>
        <Point X="305" Y="301" T="0"/>
        <Point X="306" Y="299" T="0"/>
        <Point X="307" Y="297" T="0"/>
        <Point X="307" Y="294" T="0"/>
        <Point X="308" Y="291" T="0"/>
        <Point X="310" Y="287" T="0"/>
        <Point X="311" Y="283" T="0"/>
        <Point X="313" Y="279" T="0"/>
        <Point X="314" Y="275" T="0"/>
        <Point X="315" Y="271" T="0"/>
        <Point X="317" Y="266" T="0"/>
        <Point X="319" Y="260" T="0"/>
        <Point X="321" Y="255" T="0"/>
        <Point X="323" Y="249" T="0"/>
        <Point X="325" Y="244" T="0"/>
        <Point X="326" Y="238" T="0"/>
        <Point X="329" Y="232" T="0"/>
        <Point X="330" Y="225" T="0"/>
        <Point X="332" Y="219" T="0"/>
        <Point X="334" Y="213" T="0"/>
        <Point X="336" Y="207" T="0"/>
        <Point X="337" Y="201" T="0"/>
        <Point X="338" Y="196" T="0"/>
        <Point X="340" Y="189" T="0"/>
        <Point X="341" Y="184" T="0"/>
        <Point X="343" Y="178" T="0"/>
        <Point X="344" Y="173" T="0"/>
        <Point X="345" Y="168" T="0"/>
        <Point X="347" Y="163" T="0"/>
        <Point X="348" Y="157" T="0"/>
        <Point X="350" Y="153" T="0"/>
        <Point X="352" Y="149" T="0"/>
        <Point X="353" Y="146" T="0"/>
        <Point X="355" Y="142" T="0"/>
        <Point X="356" Y="138" T="0"/>
        <Point X="357" Y="134" T="0"/>
        <Point X="359" Y="132" T="0"/>
        <Point X="361" Y="129" T="0"/>
        <Point X="363" Y="126" T="0"/>
        <Point X="364" Y="124" T="0"/>
        <Point X="367" Y="122" T="0"/>
        <Point X="368" Y="120" T="0"/>
        <Point X="371" Y="118" T="0"/>
        <Point X="372" Y="117" T="0"/>
        <Point X="374" Y="116" T="0"/>
        <Point X="375" Y="115" T="0"/>
        <Point X="377" Y="115" T="0"/>
        <Point X="378" Y="114" T="0"/>
        <Point X="379" Y="114" T="0"/>
        <Point X="381" Y="114" T="0"/>
        <Point X="382" Y="116" T="0"/>
        <Point X="384" Y="117" T="0"/>
        <Point X="386" Y="118" T="0"/>
        <Point X="387" Y="120" T="0"/>
        <Point X="389" Y="122" T="0"/>
        <Point X="390" Y="124" T="0"/>
        <Point X="392" Y="127" T="0"/>
        <Point X="393" Y="131" T="0"/>
        <Point X="394" Y="134" T="0"/>
        <Point X="396" Y="138" T="0"/>
        <Point X="397" Y="144" T="0"/>
        <Point X="399" Y="148" T="0"/>
        <Point X="401" Y="152" T="0"/>
        <Point X="402" Y="157" T="0"/>
        <Point X="404" Y="162" T="0"/>
        <Point X="405" Y="168" T="0"/>
        <Point X="407" Y="174" T="0"/>
        <Point X="408" Y="179" T="0"/>
        <Point X="410" Y="185" T="0"/>
        <Point X="412" Y="191" T="0"/>
        <Point X="413" Y="197" T="0"/>
        <Point X="416" Y="203" T="0"/>
        <Point X="417" Y="211" T="0"/>
        <Point X="420" Y="217" T="0"/>
        <Point X="421" Y="223" T="0"/>
        <Point X="423" Y="229" T="0"/>
        <Point X="425" Y="236" T="0"/>
        <Point X="427" Y="242" T="0"/>
        <Point X="429" Y="249" T="0"/>
        <Point X="431" Y="254" T="0"/>
        <Point X="434" Y="260" T="0"/>
        <Point X="440" Y="276" T="0"/>
        <Point X="442" Y="281" T="0"/>
        <Point X="445" Y="286" T="0"/>
        <Point X="446" Y="290" T="0"/>
        <Point X="449" Y="294" T="0"/>
        <Point X="450" Y="298" T="0"/>
        <Point X="452" Y="300" T="0"/>
        <Point X="454" Y="304" T="0"/>
        <Point X="456" Y="306" T="0"/>
        <Point X="457" Y="308" T="0"/>
        <Point X="457" Y="311" T="0"/>
        <Point X="458" Y="312" T="0"/>
        <Point X="459" Y="314" T="0"/>
        <Point X="459" Y="316" T="0"/>
        <Point X="459" Y="320" T="0"/>
        <Point X="458" Y="321" T="0"/>
        <Point X="457" Y="323" T="0"/>
        <Point X="455" Y="324" T="0"/>
        <Point X="453" Y="325" T="0"/>
        <Point X="451" Y="326" T="0"/>
        <Point X="449" Y="327" T="0"/>
        <Point X="442" Y="328" T="0"/>
        <Point X="439" Y="329" T="0"/>
        <Point X="435" Y="329" T="0"/>
        <Point X="431" Y="329" T="0"/>
        <Point X="427" Y="329" T="0"/>
        <Point X="422" Y="329" T="0"/>
        <Point X="416" Y="329" T="0"/>
        <Point X="411" Y="329" T="0"/>
        <Point X="405" Y="329" T="0"/>
        <Point X="400" Y="329" T="0"/>
        <Point X="394" Y="328" T="0"/>
        <Point X="388" Y="328" T="0"/>
        <Point X="382" Y="328" T="0"/>
        <Point X="376" Y="327" T="0"/>
        <Point X="371" Y="327" T="0"/>
        <Point X="366" Y="327" T="0"/>
        <Point X="360" Y="327" T="0"/>
        <Point X="356" Y="327" T="0"/>
        <Point X="351" Y="327" T="0"/>
        <Point X="347" Y="327" T="0"/>
        <Point X="342" Y="326" T="0"/>
        <Point X="338" Y="326" T="0"/>
        <Point X="335" Y="326" T="0"/>
        <Point X="332" Y="326" T="0"/>
        <Point X="328" Y="326" T="0"/>
        <Point X="323" Y="326" T="0"/>
        <Point X="319" Y="326" T="0"/>
        <Point X="317" Y="326" T="0"/>
        <Point X="315" Y="326" T="0"/>
        <Point X="314" Y="325" T="0"/>
        <Point X="313" Y="325" T="0"/>
    </Stroke>
    <Stroke index="2">
        <Point X="288" Y="219" T="0"/>
        <Point X="287" Y="218" T="0"/>
        <Point X="285" Y="217" T="0"/>
        <Point X="284" Y="216" T="0"/>
        <Point X="284" Y="214" T="0"/>
        <Point X="283" Y="214" T="0"/>
        <Point X="283" Y="216" T="0"/>
        <Point X="283" Y="217" T="0"/>
        <Point X="283" Y="218" T="0"/>
        <Point X="288" Y="225" T="0"/>
        <Point X="289" Y="228" T="0"/>
        <Point X="291" Y="231" T="0"/>
        <Point X="293" Y="236" T="0"/>
        <Point X="296" Y="239" T="0"/>
        <Point X="299" Y="244" T="0"/>
        <Point X="302" Y="249" T="0"/>
        <Point X="306" Y="256" T="0"/>
        <Point X="309" Y="261" T="0"/>
        <Point X="312" Y="266" T="0"/>
        <Point X="315" Y="272" T="0"/>
        <Point X="318" Y="276" T="0"/>
        <Point X="322" Y="282" T="0"/>
        <Point X="334" Y="303" T="0"/>
        <Point X="337" Y="308" T="0"/>
        <Point X="347" Y="324" T="0"/>
        <Point X="352" Y="334" T="0"/>
        <Point X="356" Y="338" T="0"/>
        <Point X="363" Y="351" T="0"/>
        <Point X="366" Y="355" T="0"/>
        <Point X="368" Y="358" T="0"/>
        <Point X="371" Y="362" T="0"/>
        <Point X="374" Y="365" T="0"/>
        <Point X="376" Y="368" T="0"/>
        <Point X="378" Y="371" T="0"/>
        <Point X="380" Y="373" T="0"/>
        <Point X="382" Y="374" T="0"/>
        <Point X="383" Y="376" T="0"/>
        <Point X="386" Y="377" T="0"/>
        <Point X="387" Y="378" T="0"/>
        <Point X="389" Y="379" T="0"/>
        <Point X="390" Y="379" T="0"/>
        <Point X="392" Y="379" T="0"/>
        <Point X="393" Y="380" T="0"/>
        <Point X="394" Y="380" T="0"/>
        <Point X="397" Y="380" T="0"/>
        <Point X="398" Y="379" T="0"/>
        <Point X="400" Y="378" T="0"/>
        <Point X="401" Y="376" T="0"/>
        <Point X="403" Y="375" T="0"/>
        <Point X="406" Y="370" T="0"/>
        <Point X="408" Y="367" T="0"/>
        <Point X="409" Y="363" T="0"/>
        <Point X="412" Y="354" T="0"/>
        <Point X="414" Y="349" T="0"/>
        <Point X="416" Y="343" T="0"/>
        <Point X="417" Y="338" T="0"/>
        <Point X="420" Y="332" T="0"/>
        <Point X="421" Y="326" T="0"/>
        <Point X="423" Y="321" T="0"/>
        <Point X="425" Y="314" T="0"/>
        <Point X="427" Y="306" T="0"/>
        <Point X="431" Y="293" T="0"/>
        <Point X="434" Y="286" T="0"/>
        <Point X="436" Y="279" T="0"/>
        <Point X="438" Y="272" T="0"/>
        <Point X="442" Y="264" T="0"/>
        <Point X="443" Y="257" T="0"/>
        <Point X="446" Y="251" T="0"/>
        <Point X="447" Y="245" T="0"/>
        <Point X="450" Y="239" T="0"/>
        <Point X="451" Y="233" T="0"/>
        <Point X="453" Y="228" T="0"/>
        <Point X="454" Y="224" T="0"/>
        <Point X="456" Y="219" T="0"/>
        <Point X="457" Y="215" T="0"/>
        <Point X="458" Y="212" T="0"/>
        <Point X="460" Y="208" T="0"/>
        <Point X="460" Y="205" T="0"/>
        <Point X="461" Y="203" T="0"/>
        <Point X="461" Y="201" T="0"/>
        <Point X="462" Y="199" T="0"/>
        <Point X="462" Y="198" T="0"/>
        <Point X="462" Y="197" T="0"/>
        <Point X="462" Y="195" T="0"/>
        <Point X="462" Y="194" T="0"/>
        <Point X="461" Y="193" T="0"/>
        <Point X="460" Y="192" T="0"/>
        <Point X="458" Y="191" T="0"/>
        <Point X="457" Y="191" T="0"/>
        <Point X="454" Y="190" T="0"/>
        <Point X="452" Y="190" T="0"/>
        <Point X="449" Y="190" T="0"/>
        <Point X="446" Y="190" T="0"/>
        <Point X="442" Y="190" T="0"/>
        <Point X="438" Y="191" T="0"/>
        <Point X="433" Y="191" T="0"/>
        <Point X="427" Y="192" T="0"/>
        <Point X="422" Y="193" T="0"/>
        <Point X="416" Y="194" T="0"/>
        <Point X="408" Y="194" T="0"/>
        <Point X="402" Y="196" T="0"/>
        <Point X="396" Y="197" T="0"/>
        <Point X="388" Y="198" T="0"/>
        <Point X="381" Y="199" T="0"/>
        <Point X="373" Y="199" T="0"/>
        <Point X="365" Y="200" T="0"/>
        <Point X="359" Y="201" T="0"/>
        <Point X="352" Y="202" T="0"/>
        <Point X="345" Y="203" T="0"/>
        <Point X="339" Y="204" T="0"/>
        <Point X="333" Y="206" T="0"/>
        <Point X="326" Y="206" T="0"/>
        <Point X="321" Y="207" T="0"/>
        <Point X="316" Y="208" T="0"/>
        <Point X="311" Y="208" T="0"/>
        <Point X="306" Y="209" T="0"/>
        <Point X="302" Y="209" T="0"/>
        <Point X="297" Y="210" T="0"/>
        <Point X="293" Y="210" T="0"/>
        <Point X="290" Y="211" T="0"/>
        <Point X="282" Y="211" T="0"/>
        <Point X="280" Y="211" T="0"/>
        <Point X="278" Y="212" T="0"/>
        <Point X="277" Y="212" T="0"/>
        <Point X="276" Y="213" T="0"/>
        <Point X="276" Y="214" T="0"/>
        <Point X="275" Y="215" T="0"/>
    </Stroke>
</Gesture>
