<?xml version="1.0" ?>
<Gesture Name="right_sq_bracket~10" Subject="4" Number="10" NumPts="59" InputType="Trackpad" Speed="MEDIUM">
    <Stroke index="1">
        <Point X="341" Y="78" T="0"/>
        <Point X="342" Y="78" T="0"/>
        <Point X="343" Y="78" T="0"/>
        <Point X="345" Y="78" T="0"/>
        <Point X="347" Y="78" T="0"/>
        <Point X="350" Y="78" T="0"/>
        <Point X="355" Y="78" T="0"/>
        <Point X="360" Y="79" T="0"/>
        <Point X="365" Y="79" T="0"/>
        <Point X="371" Y="80" T="0"/>
        <Point X="377" Y="80" T="0"/>
        <Point X="384" Y="80" T="0"/>
        <Point X="390" Y="80" T="0"/>
        <Point X="394" Y="80" T="0"/>
        <Point X="398" Y="81" T="0"/>
        <Point X="398" Y="83" T="0"/>
        <Point X="398" Y="84" T="0"/>
        <Point X="398" Y="86" T="0"/>
        <Point X="398" Y="88" T="0"/>
        <Point X="398" Y="89" T="0"/>
        <Point X="398" Y="91" T="0"/>
        <Point X="398" Y="94" T="0"/>
        <Point X="398" Y="99" T="0"/>
        <Point X="398" Y="104" T="0"/>
        <Point X="398" Y="108" T="0"/>
        <Point X="398" Y="114" T="0"/>
        <Point X="398" Y="118" T="0"/>
        <Point X="398" Y="124" T="0"/>
        <Point X="398" Y="128" T="0"/>
        <Point X="398" Y="132" T="0"/>
        <Point X="398" Y="135" T="0"/>
        <Point X="398" Y="138" T="0"/>
        <Point X="399" Y="141" T="0"/>
        <Point X="399" Y="143" T="0"/>
        <Point X="399" Y="145" T="0"/>
        <Point X="400" Y="147" T="0"/>
        <Point X="400" Y="149" T="0"/>
        <Point X="400" Y="151" T="0"/>
        <Point X="400" Y="152" T="0"/>
        <Point X="400" Y="154" T="0"/>
        <Point X="401" Y="156" T="0"/>
        <Point X="401" Y="157" T="0"/>
        <Point X="401" Y="159" T="0"/>
        <Point X="401" Y="160" T="0"/>
        <Point X="401" Y="161" T="0"/>
        <Point X="401" Y="162" T="0"/>
        <Point X="398" Y="163" T="0"/>
        <Point X="397" Y="163" T="0"/>
        <Point X="393" Y="164" T="0"/>
        <Point X="387" Y="164" T="0"/>
        <Point X="380" Y="164" T="0"/>
        <Point X="370" Y="164" T="0"/>
        <Point X="360" Y="165" T="0"/>
        <Point X="349" Y="165" T="0"/>
        <Point X="337" Y="165" T="0"/>
        <Point X="326" Y="166" T="0"/>
        <Point X="317" Y="166" T="0"/>
        <Point X="311" Y="166" T="0"/>
        <Point X="307" Y="166" T="0"/>
    </Stroke>
</Gesture>
